{
  "json": [
    {
      "no": 1,
      "note_prefeb_path": "CH_Event_Honglan_Note",
      "note_duration": 2.5,
      "judge_perfect": 1.8,
      "judge_good": 1.1,
      "judge_bad": 0.4,
      "note_phase": 150,
      "phase_perfect": 1.0,
      "phase_good": 0.8,
      "phase_bad": 0.5,
      "point_perfect": 1000,
      "point_good": 800,
      "point_bad": 500
    },
    {
      "no": 2,
      "note_type": 1,
      "note_prefeb_path": "CH_Event_Honglan_Note",
      "note_duration": 2.5,
      "touch_count": 5,
      "judge_perfect": 5.0,
      "judge_good": 3.0,
      "judge_bad": 1.0,
      "note_phase": 300,
      "phase_perfect": 1.0,
      "phase_good": 0.8,
      "phase_bad": 0.5,
      "point_perfect": 1000,
      "point_good": 800,
      "point_bad": 500
    },
    {
      "no": 3,
      "note_type": 2,
      "note_prefeb_path": "CH_Event_Honglan_Note",
      "note_duration": 5.0,
      "touch_count": 10,
      "judge_perfect": 10.0,
      "judge_good": 10.0,
      "judge_bad": 10.0,
      "note_phase": 500,
      "phase_perfect": 1.0,
      "phase_good": 0.8,
      "phase_bad": 0.5,
      "point_perfect": 3000
    }
  ]
}
